LICENSE
README.md
setup.py
NlpToolkit_PosTagger.egg-info/PKG-INFO
NlpToolkit_PosTagger.egg-info/SOURCES.txt
NlpToolkit_PosTagger.egg-info/dependency_links.txt
NlpToolkit_PosTagger.egg-info/requires.txt
NlpToolkit_PosTagger.egg-info/top_level.txt
PosTagger/DummyPosTagger.py
PosTagger/HmmPosTagger.py
PosTagger/NaivePosTagger.py
PosTagger/PosTaggedCorpus.py
PosTagger/PosTaggedWord.py
PosTagger/PosTagger.py
PosTagger/__init__.py