Metadata-Version: 2.1
Name: NlpToolkit-PosTagger
Version: 1.0.7
Summary: English PosTagger Library
Home-page: https://github.com/StarlangSoftware/PosTagger-Py
Author: olcaytaner
Author-email: olcay.yildiz@ozyegin.edu.tr
License: UNKNOWN
Platform: UNKNOWN
License-File: LICENSE
